ubpe/__init__.py
ubpe-0.2.3.dist-info/METADATA
ubpe-0.2.3.dist-info/WHEEL
ubpe-0.2.3.dist-info/licenses/LICENSE
ubpe-0.2.3.dist-info/RECORD
