Metadata-Version: 2.4
Name: ubpe
Version: 0.2.3
Summary: UBPE Tokenizer
License-File: LICENSE
Author: Scurrra (Ilja Baroŭski)
Author-email: iscurrra@gmail.com
Requires-Python: >=3.12
Classifier: Programming Language :: Python :: 3
Classifier: Development Status :: 4 - Beta
Provides-Extra: cython
Provides-Extra: native
Requires-Dist: ubpe-cython (>=0.2.3) ; extra == "cython"
Requires-Dist: ubpe-native (>=0.2.3) ; extra == "native"
Project-URL: Issues, https://github.com/Scurrra/ubpe/issues
Project-URL: Repository, https://github.com/Scurrra/ubpe.git
